github_tool.py
github_tool-1.0.1.dist-info/LICENSE
github_tool-1.0.1.dist-info/METADATA
github_tool-1.0.1.dist-info/WHEEL
github_tool-1.0.1.dist-info/entry_points.txt
github_tool-1.0.1.dist-info/top_level.txt
github_tool-1.0.1.dist-info/RECORD
