Metadata-Version: 2.1
Name: github-tool
Version: 1.0.1
Summary: Commandline search tool for github
Home-page: https://github.com/nlitsme/githubtool/
Author: Willem Hengeveld
Author-email: itsme@xs4all.nl
License: MIT
Keywords: github commandline
Platform: UNKNOWN
Classifier: Environment :: Console
Classifier: Intended Audience :: End Users/Desktop
Classifier: Intended Audience :: Developers
Classifier: License :: OSI Approved :: MIT License
Classifier: Operating System :: OS Independent
Classifier: Programming Language :: Python :: 3.7
Classifier: Topic :: Utilities
Classifier: Framework :: AsyncIO
Classifier: Topic :: Software Development :: Version Control :: Git
Requires-Python: >=3.7
Requires-Dist: aiohttp (==3.6.2)
